clients/__init__.py
clients/client_device.py
communication/__init__.py
communication/connection.py
encryption/__init__.py
encryption/encryption.py
models/__init__.py
models/abstract_model.py
models/pytorch_model.py
models/tensorflow_model.py
utils/__init__.py
utils/decorators.py
FederatedCryptix-1.0.0.dist-info/METADATA
FederatedCryptix-1.0.0.dist-info/WHEEL
FederatedCryptix-1.0.0.dist-info/top_level.txt
FederatedCryptix-1.0.0.dist-info/RECORD
