Metadata-Version: 2.1
Name: FederatedCryptix
Version: 1.0.0
Summary: FederatedCryptix is an innovative and modular framework designed for federated learning with a strong focus on cryptographic security.
Home-page: https://github.com/mehrdaddjavadi/FederatedCryptix
Author: Mehrdad Javadi
Author-email: mehrdaddjavadi@gmail.com
License: UNKNOWN
Keywords: federated learning,machine learning,deep learning,active learning,encryption,homomorphic encryption,FederatedCryptix
Platform: UNKNOWN
Classifier: Development Status :: 4 - Beta
Classifier: Intended Audience :: Developers
Classifier: Intended Audience :: Education
Classifier: Intended Audience :: Science/Research
Classifier: Programming Language :: Python :: 3
Classifier: Programming Language :: Python :: 3.6
Classifier: Programming Language :: Python :: 3.7
Classifier: Programming Language :: Python :: 3.8
Classifier: Programming Language :: Python :: 3.9
Classifier: Programming Language :: Python :: 3.10
Classifier: Topic :: Software Development :: Libraries :: Python Modules
Classifier: Topic :: Scientific/Engineering :: Artificial Intelligence
Requires-Python: >=3.6
Requires-Dist: numpy
Requires-Dist: tensorflow
Requires-Dist: websockets
Requires-Dist: pytest
Requires-Dist: tenseal
